{
  "timestamp": "2025-10-27T18:44:41.688213",
  "prometheus_url": "http://177.93.132.48:9090",
  "scrape_interval": 300,
  "analysis_time_seconds": 2.65,
  "metrics": {
    "cpu": {},
    "memory": {},
    "disk": {},
    "network": {}
  },
  "analysis": {
    "cpu": {
      "status": "OK",
      "severity": "✅",
      "overall_score": 0.0,
      "utilization": 0,
      "load_average": 0,
      "load_normalized": 0.0,
      "cpu_count": 1,
      "recommendations": []
    },
    "memory": {
      "status": "OK",
      "severity": "✅",
      "overall_score": 0.0,
      "utilization": 0,
      "swap_utilization": 0,
      "recommendations": []
    },
    "disk": {
      "status": "OK",
      "severity": "✅",
      "overall_score": 0.0,
      "throughput_mbps": 0.0,
      "utilization": 0,
      "read_mbps": 0.0,
      "write_mbps": 0.0,
      "recommendations": []
    },
    "network": {
      "status": "OK",
      "severity": "✅",
      "overall_score": 0.0,
      "throughput_mbps": 0.0,
      "receive_mbps": 0.0,
      "transmit_mbps": 0.0,
      "recommendations": []
    }
  },
  "overall_score": 0.0,
  "overall_status": "HEALTHY",
  "overall_severity": "✅",
  "critical_issues": [],
  "warning_issues": [],
  "all_recommendations": []
}